<?xml version="1.0" encoding="utf-8"?>
<CallableObject guid="65abf24d-02bd-496d-87bc-ca2ab85eaf10" name="DPLeaveEventGroup" description="DPLeave Event Group" namespace="GeneXus.Programs">
  <Signature name="Par">
    <Parameter name="FromDate">
      <Field>
        <Properties>
          <Property>
            <Name>Type</Name>
            <Value>Date</Value>
          </Property>
          <Property>
            <Name>Length</Name>
            <Value>8</Value>
          </Property>
        </Properties>
      </Field>
    </Parameter>
    <Parameter name="ToDate">
      <Field>
        <Properties>
          <Property>
            <Name>Type</Name>
            <Value>Date</Value>
          </Property>
          <Property>
            <Name>Length</Name>
            <Value>8</Value>
          </Property>
        </Properties>
      </Field>
    </Parameter>
    <Parameter name="CompanyLocationId">
      <Field>
        <Properties>
          <Property>
            <Name>Type</Name>
            <Value>Numeric</Value>
          </Property>
          <Property>
            <Name>Length</Name>
            <Value>10</Value>
          </Property>
        </Properties>
      </Field>
    </Parameter>
    <Parameter name="EmployeeIds" collection="true">
      <Field>
        <Properties>
          <Property>
            <Name>Type</Name>
            <Value>Numeric</Value>
          </Property>
          <Property>
            <Name>Length</Name>
            <Value>10</Value>
          </Property>
        </Properties>
      </Field>
    </Parameter>
    <Parameter name="ReturnValue" accessor="out" collection="true">
      <Field name="SDTLeaveEventGroup" description="SDTLeave Event Group">
        <Fields>
          <Field name="id" description="id">
            <Properties>
              <Property>
                <Name>Type</Name>
                <Value>Numeric</Value>
              </Property>
              <Property>
                <Name>Length</Name>
                <Value>4</Value>
              </Property>
              <Property>
                <Name>Picture</Name>
                <Value>ZZZ9</Value>
              </Property>
            </Properties>
          </Field>
          <Field name="content" description="content">
            <Properties>
              <Property>
                <Name>Type</Name>
                <Value>Character</Value>
              </Property>
              <Property>
                <Name>Length</Name>
                <Value>20</Value>
              </Property>
            </Properties>
          </Field>
        </Fields>
      </Field>
    </Parameter>
  </Signature>
</CallableObject>